CHANGELOG.md
domore/__init__.py
domore/__main__.py
domore/app/__init__.py
domore/app/main.py
domore/app/routers/__init__.py
domore/app/routers/debug.py
domore/app/routers/debugtalk.py
domore/app/routers/deps.py
domore/builtin/__init__.py
domore/builtin/comparators.py
domore/builtin/functions.py
domore/cli.py
domore/client.py
domore/compat.py
domore/exceptions.py
domore/ext/__init__.py
domore/ext/har2case/__init__.py
domore/ext/har2case/core.py
domore/ext/har2case/utils.py
domore/ext/locust/__init__.py
domore/ext/locust/locustfile.py
domore/ext/uploader/__init__.py
domore/loader.py
domore/make.py
domore/models.py
domore/parser.py
domore/response.py
domore/runner.py
domore/scaffold.py
domore/testcase.py
domore/utils.py
domore_api-0.1.7.dist-info/LICENSE
domore_api-0.1.7.dist-info/METADATA
domore_api-0.1.7.dist-info/WHEEL
domore_api-0.1.7.dist-info/entry_points.txt
domore_api-0.1.7.dist-info/RECORD
