Metadata-Version: 2.1
Name: domore-api
Version: 0.1.7
Summary: Easily do more testing for API.
License: Apache-2.0
Keywords: HTTP,api,test,requests,locustio
Author: evan.zhang
Requires-Python: >=3.7,<4.0
Classifier: Development Status :: 5 - Production/Stable
Classifier: License :: OSI Approved :: Apache Software License
Classifier: Operating System :: MacOS
Classifier: Operating System :: Microsoft :: Windows
Classifier: Operating System :: POSIX :: Linux
Classifier: Programming Language :: Python :: 3
Classifier: Programming Language :: Python :: 3.7
Classifier: Programming Language :: Python :: 3.8
Classifier: Programming Language :: Python :: 3.9
Classifier: Programming Language :: Python :: 3.10
Classifier: Programming Language :: Python :: 3.11
Classifier: Programming Language :: Python :: 3.10
Classifier: Programming Language :: Python :: 3.11
Classifier: Programming Language :: Python :: 3.7
Classifier: Programming Language :: Python :: 3.8
Classifier: Programming Language :: Python :: 3.9
Classifier: Topic :: Software Development :: Libraries :: Python Modules
Classifier: Topic :: Software Development :: Quality Assurance
Classifier: Topic :: Software Development :: Testing
Provides-Extra: allure
Provides-Extra: locust
Provides-Extra: upload
Requires-Dist: Brotli (>=1.0.9,<2.0.0)
Requires-Dist: allure-pytest (>=2.13.2,<3.0.0) ; extra == "allure"
Requires-Dist: black (>=22.3.0,<23.0.0)
Requires-Dist: filetype (>=1.0.7,<2.0.0) ; extra == "upload"
Requires-Dist: jinja2 (>=3.0.3,<4.0.0)
Requires-Dist: jmespath (>=0.9.5,<0.10.0)
Requires-Dist: locust (>=1.0.3,<2.0.0) ; extra == "locust"
Requires-Dist: loguru (>=0.4.1,<0.5.0)
Requires-Dist: pydantic (>=1.8,<1.9)
Requires-Dist: pytest (>=7.1.1,<8.0.0)
Requires-Dist: pytest-html (==4.0.0rc6)
Requires-Dist: pyyaml (>=6.0.1,<7.0.0)
Requires-Dist: requests (>=2.22.0,<3.0.0)
Requires-Dist: requests-toolbelt (>=0.9.1,<0.10.0) ; extra == "upload"
Requires-Dist: sentry-sdk (>=0.14.4,<0.15.0)
